{
  "title": "OwnableValidator",
  "signer": "0xa1E8F5D6cCd82f2a2aC4ca5df4D51c71e48a54d5",
  "auditor": {
    "name": "Ackee Blockchain",
    "uri": "https://ackee.xyz",
    "authors": [
      "Štěpán Šonský",
      "Michal Převrátil",
      "Naoki Yoshida",
      "Jan Převrátil",
      "Josef Gattermayer, Ph.D."
    ]
  },
  "reportUrl": "https://github.com/Ackee-Blockchain/public-audit-reports/blob/master/2024/ackee-blockchain-rhinestone-core-modules-report.pdf",
  "moduleAttributes": {
    "moduleAddress": "0x2483DA3A338895199E5e538530213157e931Bf06",
    "globalAttributes": {
      "reentrancyProtection": true,
      "importantDataValidation": true,
      "inputManipulationProtection": true,
      "emitsEvents": true,
      "moduleOwnerCantRug": true,
      "upgradeable": false,
      "pausable": false,
      "licensedModule": false,
      "erc7562StorageCompliant": true,
      "uninstallCleanUp": true,
      "multichainCompatible": false
    },
    "validatorAttributes": {
      "unscopedValidator": true,
      "recoveryModule": false,
      "multiplexer": true
    },
    "executorAttributes": {
      "handlesUserAssets": false,
      "delegateCall": false,
      "triggeredByAccount": false,
      "triggeredByRelayer": false,
      "deterministicExecution": false
    },
    "fallbackAttributes": {
      "compatibilityFeature": false,
      "callbacks": false
    },
    "hookAttributes": {
      "defaultAllow": false,
      "defaultDeny": false,
      "accessControl": false,
      "moduleControl": false,
      "userControl": false
    },
    "externalDependency": {
      "oracle": false,
      "bridges": false,
      "dexs": false,
      "vaults": false,
      "registry": false,
      "lending": false,
      "liquidityProvision": false,
      "governance": false,
      "privacy": false,
      "zkProvers": false,
      "ercDeps": []
    }
  },
  "signature": {
    "hash": "0x1a6f3ccc3779243fe418b03cbc7bf206923a4236b414673140cb8ad84290c0d7",
    "signature": "0xaf054f0d872685a57507d362efa2235d4a7c92fcc992a536a0d609f246399e426a5f67f709868ce92ddf37f9fc7626f6b62ac7f8b3ce7208fbbc9905712525f701"
  }
}